{
  "window": {
    "width": 1200,
    "height": 800,
    "title": "AI Sketch Duel",
    "resizable": true,
    "fullscreen": false,
    "vsync": true,
    "fps_limit": 60
  },
  "colors": {
    "primary": [74, 144, 226],
    "secondary": [156, 39, 176],
    "accent": [255, 193, 7],
    "background": [18, 18, 18],
    "surface": [33, 33, 33],
    "text_primary": [255, 255, 255],
    "text_secondary": [189, 189, 189],
    "text_disabled": [117, 117, 117],
    "success": [76, 175, 80],
    "warning": [255, 152, 0],
    "error": [244, 67, 54],
    "info": [33, 150, 243],
    "glass_background": [255, 255, 255, 20],
    "glass_border": [255, 255, 255, 40]
  },
  "fonts": {
    "primary_font": "Arial",
    "secondary_font": "Helvetica",
    "monospace_font": "Courier New",
    "title_size": 32,
    "heading_size": 24,
    "body_size": 16,
    "caption_size": 12,
    "small_size": 10,
    "title_bold": true,
    "heading_bold": true,
    "body_bold": false
  },
  "layout": {
    "margin_small": 8,
    "margin_medium": 16,
    "margin_large": 24,
    "margin_xlarge": 32,
    "button_height": 40,
    "input_height": 36,
    "panel_min_width": 200,
    "panel_min_height": 150,
    "whiteboard_width": 600,
    "whiteboard_height": 400,
    "whiteboard_border_width": 2,
    "chat_panel_width": 300,
    "chat_panel_height": 400,
    "chat_message_height": 30,
    "chat_max_messages": 50,
    "live2d_model_width": 200,
    "live2d_model_height": 300,
    "live2d_position_x": 50,
    "live2d_position_y": 50,
    "border_radius_small": 4,
    "border_radius_medium": 8,
    "border_radius_large": 12
  },
  "animation": {
    "fade_duration": 300,
    "slide_duration": 250,
    "scale_duration": 200,
    "easing_type": "ease_out",
    "enable_animations": true,
    "enable_transitions": true,
    "enable_particle_effects": true,
    "particle_count": 50,
    "particle_lifetime": 2.0,
    "particle_speed": 100.0
  },
  "show_fps": false,
  "show_debug_info": false,
  "enable_tooltips": true,
  "tooltip_delay": 500
}